[
  {
    "id": "NASDAQ_15M_Trendline_29093.00_29196.76_28781.72",
    "symbol": "NASDAQ",
    "timeframe": "15M",
    "strategy": "Trendline",
    "signal": "SELL",
    "entry": "29093.00",
    "sl": "29196.76",
    "tp": "28781.72",
    "status": "Active",
    "trade_time": "19 May 11:51 pm",
    "time_identified": "2026-05-19 18:21:37"
  },
  {
    "id": "EURUSD_5M_Trendline_1.16158_1.16208_1.16050",
    "symbol": "EURUSD",
    "timeframe": "5M",
    "strategy": "Trendline",
    "signal": "SELL",
    "entry": "1.16158",
    "sl": "1.16208",
    "tp": "1.16050",
    "status": "Active",
    "trade_time": "19 May 11:51 pm",
    "time_identified": "2026-05-19 18:21:37"
  }
]