[
  {
    "id": "NASDAQ_5M_Trendline_29226.50_29257.84_29132.48",
    "symbol": "NASDAQ",
    "timeframe": "5M",
    "strategy": "Trendline",
    "signal": "SELL",
    "entry": "29226.50",
    "sl": "29257.84",
    "tp": "29132.48",
    "status": "Active",
    "trade_time": "21 May 06:35 am",
    "time_identified": "2026-05-21 01:05:20"
  },
  {
    "id": "NASDAQ_1H_Trendline_29226.50_29315.71_28958.86",
    "symbol": "NASDAQ",
    "timeframe": "1H",
    "strategy": "Trendline",
    "signal": "SELL",
    "entry": "29226.50",
    "sl": "29315.71",
    "tp": "28958.86",
    "status": "Active",
    "trade_time": "21 May 06:35 am",
    "time_identified": "2026-05-21 01:05:20"
  },
  {
    "id": "S&P500_5M_Trendline_7423.50_7431.40_7407.50",
    "symbol": "S&P500",
    "timeframe": "5M",
    "strategy": "Trendline",
    "signal": "SELL",
    "entry": "7423.50",
    "sl": "7431.40",
    "tp": "7407.50",
    "status": "Active",
    "trade_time": "21 May 06:35 am",
    "time_identified": "2026-05-21 01:05:20"
  },
  {
    "id": "XAUUSD_5M_Trendline_4549.30_4557.74_4535.60",
    "symbol": "XAUUSD",
    "timeframe": "5M",
    "strategy": "Trendline",
    "signal": "SELL",
    "entry": "4549.30",
    "sl": "4557.74",
    "tp": "4535.60",
    "status": "Active",
    "trade_time": "21 May 06:35 am",
    "time_identified": "2026-05-21 01:05:20"
  },
  {
    "id": "XAUUSD_15M_Trendline_4549.30_4563.94_4505.39",
    "symbol": "XAUUSD",
    "timeframe": "15M",
    "strategy": "Trendline",
    "signal": "SELL",
    "entry": "4549.30",
    "sl": "4563.94",
    "tp": "4505.39",
    "status": "Active",
    "trade_time": "21 May 06:35 am",
    "time_identified": "2026-05-21 01:05:20"
  },
  {
    "id": "XAUUSD_1H_Trendline_4549.30_4586.35_4455.00",
    "symbol": "XAUUSD",
    "timeframe": "1H",
    "strategy": "Trendline",
    "signal": "SELL",
    "entry": "4549.30",
    "sl": "4586.35",
    "tp": "4455.00",
    "status": "Active",
    "trade_time": "21 May 06:35 am",
    "time_identified": "2026-05-21 01:05:20"
  }
]