[
  {
    "id": "NASDAQ_5M_18_May_0833_pm",
    "symbol": "NASDAQ",
    "timeframe": "5M",
    "strategy": "Trendline",
    "signal": "BUY",
    "entry": "29089.25",
    "sl": "28902.72",
    "tp": "29419.75",
    "status": "Active",
    "trade_time": "18 May 08:33 pm",
    "time_identified": "2026-05-18 15:03:36"
  },
  {
    "id": "GBPUSD_1H_18_May_0833_pm",
    "symbol": "GBPUSD",
    "timeframe": "1H",
    "strategy": "Trendline",
    "signal": "SELL",
    "entry": "1.33878",
    "sl": "1.34197",
    "tp": "1.33039",
    "status": "Active",
    "trade_time": "18 May 08:33 pm",
    "time_identified": "2026-05-18 15:03:36"
  }
]